ozapfdis/__init__.py
ozapfdis/git.py
ozapfdis/glob.py
ozapfdis/jdeps.py
ozapfdis/linux/__init__.py
ozapfdis/linux/vmstat.py
ozapfdis-0.0.2.dist-info/LICENSE
ozapfdis-0.0.2.dist-info/METADATA
ozapfdis-0.0.2.dist-info/WHEEL
ozapfdis-0.0.2.dist-info/top_level.txt
ozapfdis-0.0.2.dist-info/RECORD
